fmdpy/__init__.py
fmdpy/__main__.py
fmdpy/api.py
fmdpy/conf.py
fmdpy/download.py
fmdpy/prompt.py
fmdpy/song.py
fmdpy/splist.py
fmdpy/stream.py
fmdpy/utils.py
fmdpy-0.6.3.dist-info/LICENSE
fmdpy-0.6.3.dist-info/METADATA
fmdpy-0.6.3.dist-info/WHEEL
fmdpy-0.6.3.dist-info/entry_points.txt
fmdpy-0.6.3.dist-info/top_level.txt
fmdpy-0.6.3.dist-info/RECORD
