Metadata-Version: 2.1
Name: fmdpy
Version: 0.6.3
Summary: Music Downloader
Home-page: https://github.com/Liupold/fmdpy
Author: Rohn Chatterjee
Author-email: rohn.ch@gmail.com
License: GPLv3
Platform: UNKNOWN
Classifier: Programming Language :: Python :: 3
Classifier: License :: OSI Approved :: GNU General Public License v3 (GPLv3)
Classifier: Operating System :: OS Independent
Classifier: Development Status :: 5 - Production/Stable
Requires-Python: >=3.7
License-File: LICENSE
Requires-Dist: click
Requires-Dist: music-tag (>=0.4.3)
Requires-Dist: requests
Requires-Dist: pillow
Requires-Dist: lyricsgenius
Requires-Dist: dataclasses
Requires-Dist: spotipy
Requires-Dist: tqdm
Requires-Dist: pydub
Requires-Dist: pycryptodome
